pymusictheory/__init__.py
pymusictheory-2.2.3.dist-info/METADATA
pymusictheory-2.2.3.dist-info/WHEEL
pymusictheory-2.2.3.dist-info/licenses/LICENSE
pymusictheory-2.2.3.dist-info/RECORD
