Metadata-Version: 2.4
Name: pymusictheory
Version: 2.2.3
Summary: A python library for doing calculations with musical notes.
Project-URL: Homepage, https://github.com/valterschutz/pymusictheory
Author-email: Valter Schütz <valterschutz@proton.me>
License: Copyright © 2025 Valter Schütz
License-File: LICENSE
Classifier: License :: OSI Approved :: MIT License
Classifier: Programming Language :: Python
Classifier: Programming Language :: Python :: 3
Classifier: Topic :: Artistic Software
Classifier: Topic :: Multimedia :: Sound/Audio :: Analysis
Requires-Python: >=3.13
